README.rst
setup.cfg
setup.py
yafte/__init__.py
yafte/yaml_fpdf_template.py
yafte.egg-info/PKG-INFO
yafte.egg-info/SOURCES.txt
yafte.egg-info/dependency_links.txt
yafte.egg-info/requires.txt
yafte.egg-info/top_level.txt