Metadata-Version: 1.1
Name: yafte
Version: 0.6.0
Summary: Using yaml for fpdf templates
Home-page: https://github.com/m42e/yamlfpdftemplate
Author: Matthias Bilger
Author-email: matthias@bilger.info
License: MIT
Download-URL: https://github.com/m42e/yamlfpdftemplate/archive/v0.6.0.tar.gz
Keywords: template yaml fpdf
Platform: UNKNOWN
Classifier: Topic :: Text Processing
Classifier: Development Status :: 3 - Alpha
Classifier: License :: OSI Approved :: MIT License
Classifier: Programming Language :: Python :: 3.5
